<ColorMaps>
<ColorMap name="ColdFire" space="RGB">
<Point x="0" r="0.0" g="0.671875" b="0.984375"/>
<Point x="1" r="0.0" g="0.671875" b="0.984375"/>
<Point x="2" r="0.0" g="0.65625" b="0.984375"/>
<Point x="3" r="0.0" g="0.640625" b="0.984375"/>
<Point x="4" r="0.0" g="0.625" b="0.984375"/>
<Point x="5" r="0.0" g="0.609375" b="0.984375"/>
<Point x="6" r="0.0" g="0.59375" b="0.984375"/>
<Point x="7" r="0.0" g="0.59375" b="0.984375"/>
<Point x="8" r="0.0" g="0.578125" b="0.984375"/>
<Point x="9" r="0.0" g="0.5625" b="0.984375"/>
<Point x="10" r="0.0" g="0.546875" b="0.984375"/>
<Point x="11" r="0.0" g="0.53125" b="0.984375"/>
<Point x="12" r="0.0" g="0.515625" b="0.984375"/>
<Point x="13" r="0.0" g="0.515625" b="0.984375"/>
<Point x="14" r="0.0" g="0.5" b="0.984375"/>
<Point x="15" r="0.0" g="0.484375" b="0.984375"/>
<Point x="16" r="0.0" g="0.46875" b="0.984375"/>
<Point x="17" r="0.0" g="0.453125" b="0.984375"/>
<Point x="18" r="0.0" g="0.4375" b="0.984375"/>
<Point x="19" r="0.0" g="0.4375" b="0.984375"/>
<Point x="20" r="0.0" g="0.421875" b="0.984375"/>
<Point x="21" r="0.0" g="0.40625" b="0.984375"/>
<Point x="22" r="0.0" g="0.390625" b="0.984375"/>
<Point x="23" r="0.0" g="0.375" b="0.984375"/>
<Point x="24" r="0.0" g="0.359375" b="0.984375"/>
<Point x="25" r="0.0" g="0.359375" b="0.984375"/>
<Point x="26" r="0.0" g="0.34375" b="0.984375"/>
<Point x="27" r="0.0" g="0.328125" b="0.984375"/>
<Point x="28" r="0.0" g="0.3125" b="0.984375"/>
<Point x="29" r="0.0" g="0.296875" b="0.984375"/>
<Point x="30" r="0.0" g="0.28125" b="0.984375"/>
<Point x="31" r="0.0" g="0.265625" b="0.984375"/>
<Point x="32" r="0.0" g="0.25" b="0.984375"/>
<Point x="33" r="0.0" g="0.234375" b="0.984375"/>
<Point x="34" r="0.0" g="0.21875" b="0.984375"/>
<Point x="35" r="0.0" g="0.203125" b="0.984375"/>
<Point x="36" r="0.0" g="0.1875" b="0.984375"/>
<Point x="37" r="0.0" g="0.171875" b="0.984375"/>
<Point x="38" r="0.0" g="0.15625" b="0.984375"/>
<Point x="39" r="0.0" g="0.140625" b="0.984375"/>
<Point x="40" r="0.0" g="0.125" b="0.984375"/>
<Point x="41" r="0.0" g="0.109375" b="0.984375"/>
<Point x="42" r="0.0" g="0.09375" b="0.984375"/>
<Point x="43" r="0.0" g="0.078125" b="0.984375"/>
<Point x="44" r="0.0" g="0.0625" b="0.984375"/>
<Point x="45" r="0.0" g="0.046875" b="0.984375"/>
<Point x="46" r="0.0" g="0.03125" b="0.984375"/>
<Point x="47" r="0.0" g="0.015625" b="0.984375"/>
<Point x="48" r="0.0" g="0.015625" b="0.984375"/>
<Point x="49" r="0.015625" g="0.015625" b="0.96875"/>
<Point x="50" r="0.015625" g="0.015625" b="0.96875"/>
<Point x="51" r="0.03125" g="0.015625" b="0.953125"/>
<Point x="52" r="0.03125" g="0.03125" b="0.9375"/>
<Point x="53" r="0.046875" g="0.03125" b="0.9375"/>
<Point x="54" r="0.046875" g="0.03125" b="0.921875"/>
<Point x="55" r="0.0625" g="0.03125" b="0.90625"/>
<Point x="56" r="0.0625" g="0.046875" b="0.90625"/>
<Point x="57" r="0.078125" g="0.046875" b="0.890625"/>
<Point x="58" r="0.078125" g="0.046875" b="0.875"/>
<Point x="59" r="0.09375" g="0.046875" b="0.875"/>
<Point x="60" r="0.09375" g="0.0625" b="0.859375"/>
<Point x="61" r="0.109375" g="0.0625" b="0.84375"/>
<Point x="62" r="0.109375" g="0.0625" b="0.84375"/>
<Point x="63" r="0.125" g="0.0625" b="0.828125"/>
<Point x="64" r="0.125" g="0.078125" b="0.828125"/>
<Point x="65" r="0.140625" g="0.078125" b="0.8125"/>
<Point x="66" r="0.140625" g="0.078125" b="0.796875"/>
<Point x="67" r="0.15625" g="0.078125" b="0.796875"/>
<Point x="68" r="0.15625" g="0.09375" b="0.78125"/>
<Point x="69" r="0.171875" g="0.09375" b="0.765625"/>
<Point x="70" r="0.171875" g="0.09375" b="0.765625"/>
<Point x="71" r="0.1875" g="0.09375" b="0.75"/>
<Point x="72" r="0.1875" g="0.09375" b="0.734375"/>
<Point x="73" r="0.203125" g="0.109375" b="0.734375"/>
<Point x="74" r="0.203125" g="0.109375" b="0.71875"/>
<Point x="75" r="0.21875" g="0.109375" b="0.703125"/>
<Point x="76" r="0.21875" g="0.109375" b="0.703125"/>
<Point x="77" r="0.234375" g="0.125" b="0.6875"/>
<Point x="78" r="0.234375" g="0.125" b="0.671875"/>
<Point x="79" r="0.25" g="0.125" b="0.671875"/>
<Point x="80" r="0.25" g="0.125" b="0.65625"/>
<Point x="81" r="0.265625" g="0.140625" b="0.65625"/>
<Point x="82" r="0.265625" g="0.140625" b="0.640625"/>
<Point x="83" r="0.28125" g="0.140625" b="0.625"/>
<Point x="84" r="0.28125" g="0.140625" b="0.625"/>
<Point x="85" r="0.296875" g="0.15625" b="0.609375"/>
<Point x="86" r="0.296875" g="0.15625" b="0.59375"/>
<Point x="87" r="0.3125" g="0.15625" b="0.59375"/>
<Point x="88" r="0.3125" g="0.15625" b="0.578125"/>
<Point x="89" r="0.328125" g="0.171875" b="0.5625"/>
<Point x="90" r="0.328125" g="0.171875" b="0.5625"/>
<Point x="91" r="0.34375" g="0.171875" b="0.546875"/>
<Point x="92" r="0.34375" g="0.171875" b="0.53125"/>
<Point x="93" r="0.359375" g="0.1875" b="0.53125"/>
<Point x="94" r="0.359375" g="0.1875" b="0.515625"/>
<Point x="95" r="0.375" g="0.1875" b="0.5"/>
<Point x="96" r="0.390625" g="0.1875" b="0.5"/>
<Point x="97" r="0.390625" g="0.1875" b="0.484375"/>
<Point x="98" r="0.40625" g="0.203125" b="0.484375"/>
<Point x="99" r="0.40625" g="0.203125" b="0.46875"/>
<Point x="100" r="0.421875" g="0.203125" b="0.453125"/>
<Point x="101" r="0.421875" g="0.203125" b="0.453125"/>
<Point x="102" r="0.4375" g="0.21875" b="0.4375"/>
<Point x="103" r="0.4375" g="0.21875" b="0.421875"/>
<Point x="104" r="0.453125" g="0.21875" b="0.421875"/>
<Point x="105" r="0.453125" g="0.21875" b="0.40625"/>
<Point x="106" r="0.46875" g="0.234375" b="0.390625"/>
<Point x="107" r="0.46875" g="0.234375" b="0.390625"/>
<Point x="108" r="0.484375" g="0.234375" b="0.375"/>
<Point x="109" r="0.484375" g="0.234375" b="0.359375"/>
<Point x="110" r="0.5" g="0.25" b="0.359375"/>
<Point x="111" r="0.5" g="0.25" b="0.34375"/>
<Point x="112" r="0.515625" g="0.25" b="0.34375"/>
<Point x="113" r="0.515625" g="0.25" b="0.328125"/>
<Point x="114" r="0.53125" g="0.265625" b="0.3125"/>
<Point x="115" r="0.53125" g="0.265625" b="0.3125"/>
<Point x="116" r="0.546875" g="0.265625" b="0.296875"/>
<Point x="117" r="0.546875" g="0.265625" b="0.28125"/>
<Point x="118" r="0.5625" g="0.28125" b="0.28125"/>
<Point x="119" r="0.5625" g="0.28125" b="0.265625"/>
<Point x="120" r="0.578125" g="0.28125" b="0.25"/>
<Point x="121" r="0.578125" g="0.28125" b="0.25"/>
<Point x="122" r="0.59375" g="0.28125" b="0.234375"/>
<Point x="123" r="0.59375" g="0.296875" b="0.21875"/>
<Point x="124" r="0.609375" g="0.296875" b="0.21875"/>
<Point x="125" r="0.609375" g="0.296875" b="0.203125"/>
<Point x="126" r="0.625" g="0.296875" b="0.1875"/>
<Point x="127" r="0.625" g="0.3125" b="0.1875"/>
<Point x="128" r="0.640625" g="0.3125" b="0.171875"/>
<Point x="129" r="0.640625" g="0.3125" b="0.171875"/>
<Point x="130" r="0.65625" g="0.3125" b="0.15625"/>
<Point x="131" r="0.65625" g="0.328125" b="0.140625"/>
<Point x="132" r="0.671875" g="0.328125" b="0.140625"/>
<Point x="133" r="0.671875" g="0.328125" b="0.125"/>
<Point x="134" r="0.6875" g="0.328125" b="0.109375"/>
<Point x="135" r="0.6875" g="0.34375" b="0.109375"/>
<Point x="136" r="0.703125" g="0.34375" b="0.09375"/>
<Point x="137" r="0.703125" g="0.34375" b="0.078125"/>
<Point x="138" r="0.71875" g="0.34375" b="0.078125"/>
<Point x="139" r="0.71875" g="0.359375" b="0.0625"/>
<Point x="140" r="0.734375" g="0.359375" b="0.046875"/>
<Point x="141" r="0.734375" g="0.359375" b="0.046875"/>
<Point x="142" r="0.75" g="0.359375" b="0.03125"/>
<Point x="143" r="0.765625" g="0.375" b="0.015625"/>
<Point x="144" r="0.765625" g="0.375" b="0.015625"/>
<Point x="145" r="0.765625" g="0.390625" b="0.015625"/>
<Point x="146" r="0.765625" g="0.390625" b="0.015625"/>
<Point x="147" r="0.765625" g="0.40625" b="0.015625"/>
<Point x="148" r="0.78125" g="0.421875" b="0.015625"/>
<Point x="149" r="0.78125" g="0.421875" b="0.015625"/>
<Point x="150" r="0.78125" g="0.4375" b="0.015625"/>
<Point x="151" r="0.78125" g="0.4375" b="0.015625"/>
<Point x="152" r="0.78125" g="0.453125" b="0.015625"/>
<Point x="153" r="0.796875" g="0.46875" b="0.015625"/>
<Point x="154" r="0.796875" g="0.46875" b="0.015625"/>
<Point x="155" r="0.796875" g="0.484375" b="0.015625"/>
<Point x="156" r="0.796875" g="0.484375" b="0.015625"/>
<Point x="157" r="0.8125" g="0.5" b="0.015625"/>
<Point x="158" r="0.8125" g="0.515625" b="0.015625"/>
<Point x="159" r="0.8125" g="0.515625" b="0.015625"/>
<Point x="160" r="0.8125" g="0.53125" b="0.015625"/>
<Point x="161" r="0.8125" g="0.53125" b="0.015625"/>
<Point x="162" r="0.828125" g="0.546875" b="0.015625"/>
<Point x="163" r="0.828125" g="0.5625" b="0.015625"/>
<Point x="164" r="0.828125" g="0.5625" b="0.015625"/>
<Point x="165" r="0.828125" g="0.578125" b="0.015625"/>
<Point x="166" r="0.84375" g="0.59375" b="0.015625"/>
<Point x="167" r="0.84375" g="0.59375" b="0.015625"/>
<Point x="168" r="0.84375" g="0.609375" b="0.015625"/>
<Point x="169" r="0.84375" g="0.609375" b="0.015625"/>
<Point x="170" r="0.84375" g="0.625" b="0.015625"/>
<Point x="171" r="0.859375" g="0.640625" b="0.015625"/>
<Point x="172" r="0.859375" g="0.640625" b="0.015625"/>
<Point x="173" r="0.859375" g="0.65625" b="0.015625"/>
<Point x="174" r="0.859375" g="0.65625" b="0.015625"/>
<Point x="175" r="0.875" g="0.671875" b="0.015625"/>
<Point x="176" r="0.875" g="0.6875" b="0.015625"/>
<Point x="177" r="0.875" g="0.6875" b="0.015625"/>
<Point x="178" r="0.875" g="0.703125" b="0.015625"/>
<Point x="179" r="0.875" g="0.703125" b="0.015625"/>
<Point x="180" r="0.890625" g="0.71875" b="0.015625"/>
<Point x="181" r="0.890625" g="0.734375" b="0.015625"/>
<Point x="182" r="0.890625" g="0.734375" b="0.015625"/>
<Point x="183" r="0.890625" g="0.75" b="0.015625"/>
<Point x="184" r="0.890625" g="0.75" b="0.015625"/>
<Point x="185" r="0.90625" g="0.765625" b="0.015625"/>
<Point x="186" r="0.90625" g="0.78125" b="0.015625"/>
<Point x="187" r="0.90625" g="0.78125" b="0.015625"/>
<Point x="188" r="0.90625" g="0.796875" b="0.015625"/>
<Point x="189" r="0.921875" g="0.8125" b="0.015625"/>
<Point x="190" r="0.921875" g="0.8125" b="0.015625"/>
<Point x="191" r="0.921875" g="0.828125" b="0.015625"/>
<Point x="192" r="0.921875" g="0.828125" b="0.015625"/>
<Point x="193" r="0.921875" g="0.84375" b="0.015625"/>
<Point x="194" r="0.9375" g="0.859375" b="0.015625"/>
<Point x="195" r="0.9375" g="0.859375" b="0.015625"/>
<Point x="196" r="0.9375" g="0.875" b="0.015625"/>
<Point x="197" r="0.9375" g="0.875" b="0.015625"/>
<Point x="198" r="0.953125" g="0.890625" b="0.015625"/>
<Point x="199" r="0.953125" g="0.90625" b="0.015625"/>
<Point x="200" r="0.953125" g="0.90625" b="0.015625"/>
<Point x="201" r="0.953125" g="0.921875" b="0.015625"/>
<Point x="202" r="0.953125" g="0.921875" b="0.015625"/>
<Point x="203" r="0.96875" g="0.9375" b="0.015625"/>
<Point x="204" r="0.96875" g="0.953125" b="0.015625"/>
<Point x="205" r="0.96875" g="0.953125" b="0.015625"/>
<Point x="206" r="0.96875" g="0.96875" b="0.015625"/>
<Point x="207" r="0.984375" g="0.984375" b="0.0"/>
<Point x="208" r="0.984375" g="0.984375" b="0.40625"/>
<Point x="209" r="0.984375" g="0.984375" b="0.40625"/>
<Point x="210" r="0.984375" g="0.984375" b="0.421875"/>
<Point x="211" r="0.984375" g="0.984375" b="0.4375"/>
<Point x="212" r="0.984375" g="0.984375" b="0.453125"/>
<Point x="213" r="0.984375" g="0.984375" b="0.46875"/>
<Point x="214" r="0.984375" g="0.984375" b="0.46875"/>
<Point x="215" r="0.984375" g="0.984375" b="0.484375"/>
<Point x="216" r="0.984375" g="0.984375" b="0.5"/>
<Point x="217" r="0.984375" g="0.984375" b="0.515625"/>
<Point x="218" r="0.984375" g="0.984375" b="0.53125"/>
<Point x="219" r="0.984375" g="0.984375" b="0.53125"/>
<Point x="220" r="0.984375" g="0.984375" b="0.546875"/>
<Point x="221" r="0.984375" g="0.984375" b="0.5625"/>
<Point x="222" r="0.984375" g="0.984375" b="0.578125"/>
<Point x="223" r="0.984375" g="0.984375" b="0.59375"/>
<Point x="224" r="0.984375" g="0.984375" b="0.59375"/>
<Point x="225" r="0.984375" g="0.984375" b="0.609375"/>
<Point x="226" r="0.984375" g="0.984375" b="0.625"/>
<Point x="227" r="0.984375" g="0.984375" b="0.640625"/>
<Point x="228" r="0.984375" g="0.984375" b="0.65625"/>
<Point x="229" r="0.984375" g="0.984375" b="0.65625"/>
<Point x="230" r="0.984375" g="0.984375" b="0.671875"/>
<Point x="231" r="0.984375" g="0.984375" b="0.6875"/>
<Point x="232" r="0.984375" g="0.984375" b="0.703125"/>
<Point x="233" r="0.984375" g="0.984375" b="0.71875"/>
<Point x="234" r="0.984375" g="0.984375" b="0.71875"/>
<Point x="235" r="0.984375" g="0.984375" b="0.734375"/>
<Point x="236" r="0.984375" g="0.984375" b="0.75"/>
<Point x="237" r="0.984375" g="0.984375" b="0.765625"/>
<Point x="238" r="0.984375" g="0.984375" b="0.78125"/>
<Point x="239" r="0.984375" g="0.984375" b="0.78125"/>
<Point x="240" r="0.984375" g="0.984375" b="0.796875"/>
<Point x="241" r="0.984375" g="0.984375" b="0.8125"/>
<Point x="242" r="0.984375" g="0.984375" b="0.828125"/>
<Point x="243" r="0.984375" g="0.984375" b="0.84375"/>
<Point x="244" r="0.984375" g="0.984375" b="0.84375"/>
<Point x="245" r="0.984375" g="0.984375" b="0.859375"/>
<Point x="246" r="0.984375" g="0.984375" b="0.875"/>
<Point x="247" r="0.984375" g="0.984375" b="0.890625"/>
<Point x="248" r="0.984375" g="0.984375" b="0.90625"/>
<Point x="249" r="0.984375" g="0.984375" b="0.90625"/>
<Point x="250" r="0.984375" g="0.984375" b="0.921875"/>
<Point x="251" r="0.984375" g="0.984375" b="0.9375"/>
<Point x="252" r="0.984375" g="0.984375" b="0.953125"/>
<Point x="253" r="0.984375" g="0.984375" b="0.96875"/>
<Point x="254" r="0.984375" g="0.984375" b="0.984375"/>
</ColorMap>
</ColorMaps>